{
  "entrypoints": [
    "main"
  ],
  "origins": {
    "237": [
      237
    ],
    "17896441": [
      869,
      401
    ],
    "main": [
      354,
      869,
      792
    ],
    "runtime~main": [
      792,
      869,
      354
    ],
    "0058b4c6": [
      849
    ],
    "0e384e19": [
      976
    ],
    "233062a5": [
      241
    ],
    "39f1c636": [
      568
    ],
    "521c1431": [
      149
    ],
    "5e95c892": [
      647
    ],
    "68087d72": [
      28
    ],
    "91afc14c": [
      267
    ],
    "95167d33": [
      963
    ],
    "a7456010": [
      235
    ],
    "a7bd4aaa": [
      98
    ],
    "a94703ab": [
      869,
      48
    ],
    "aba21aa0": [
      742
    ],
    "afc803b1": [
      435
    ],
    "b30d0db9": [
      897
    ],
    "bd49b525": [
      472
    ],
    "c4f5d8e4": [
      634
    ],
    "cd84c24b": [
      955
    ],
    "fb711c9b": [
      746
    ],
    "styles": [
      48,
      354,
      401,
      792,
      869
    ]
  },
  "assets": {
    "28": {
      "js": [
        {
          "file": "assets/js/68087d72.e5aa684c.js",
          "hash": "bc1fc168d8fe1464",
          "publicPath": "/assets/js/68087d72.e5aa684c.js"
        }
      ]
    },
    "48": {
      "js": [
        {
          "file": "assets/js/a94703ab.50efcb12.js",
          "hash": "b915794bd903ff2b",
          "publicPath": "/assets/js/a94703ab.50efcb12.js"
        }
      ]
    },
    "98": {
      "js": [
        {
          "file": "assets/js/a7bd4aaa.30cc2cb1.js",
          "hash": "fc44be172d325234",
          "publicPath": "/assets/js/a7bd4aaa.30cc2cb1.js"
        }
      ]
    },
    "149": {
      "js": [
        {
          "file": "assets/js/521c1431.71ae3239.js",
          "hash": "6bbd72526f0fde59",
          "publicPath": "/assets/js/521c1431.71ae3239.js"
        }
      ]
    },
    "235": {
      "js": [
        {
          "file": "assets/js/a7456010.7bbca5f6.js",
          "hash": "7bd5f0f7c0ab6a4d",
          "publicPath": "/assets/js/a7456010.7bbca5f6.js"
        }
      ]
    },
    "237": {
      "js": [
        {
          "file": "assets/js/237.c4209685.js",
          "hash": "5699fa8618465f86",
          "publicPath": "/assets/js/237.c4209685.js"
        }
      ]
    },
    "241": {
      "js": [
        {
          "file": "assets/js/233062a5.894bb17c.js",
          "hash": "17ddaaaedc381521",
          "publicPath": "/assets/js/233062a5.894bb17c.js"
        }
      ]
    },
    "267": {
      "js": [
        {
          "file": "assets/js/91afc14c.e70a19e6.js",
          "hash": "9f5343b0c61af610",
          "publicPath": "/assets/js/91afc14c.e70a19e6.js"
        }
      ]
    },
    "354": {
      "js": [
        {
          "file": "assets/js/runtime~main.db4e374c.js",
          "hash": "bb5f6e0782fdcd6a",
          "publicPath": "/assets/js/runtime~main.db4e374c.js"
        }
      ]
    },
    "401": {
      "js": [
        {
          "file": "assets/js/17896441.403eee85.js",
          "hash": "06fcc5597153f84f",
          "publicPath": "/assets/js/17896441.403eee85.js"
        }
      ]
    },
    "435": {
      "js": [
        {
          "file": "assets/js/afc803b1.ee39539f.js",
          "hash": "24a162283e71e560",
          "publicPath": "/assets/js/afc803b1.ee39539f.js"
        }
      ]
    },
    "472": {
      "js": [
        {
          "file": "assets/js/bd49b525.4b1f7443.js",
          "hash": "be0c882ab7794010",
          "publicPath": "/assets/js/bd49b525.4b1f7443.js"
        }
      ]
    },
    "568": {
      "js": [
        {
          "file": "assets/js/39f1c636.820dbbd4.js",
          "hash": "227b71aaa88d96b7",
          "publicPath": "/assets/js/39f1c636.820dbbd4.js"
        }
      ]
    },
    "634": {
      "js": [
        {
          "file": "assets/js/c4f5d8e4.16dc785b.js",
          "hash": "9a1d5cf44b883044",
          "publicPath": "/assets/js/c4f5d8e4.16dc785b.js"
        }
      ]
    },
    "647": {
      "js": [
        {
          "file": "assets/js/5e95c892.6587cfcb.js",
          "hash": "8e50c77a72f0f2db",
          "publicPath": "/assets/js/5e95c892.6587cfcb.js"
        }
      ]
    },
    "742": {
      "js": [
        {
          "file": "assets/js/aba21aa0.a1ddcdff.js",
          "hash": "f7fc36a25d717a36",
          "publicPath": "/assets/js/aba21aa0.a1ddcdff.js"
        }
      ]
    },
    "746": {
      "js": [
        {
          "file": "assets/js/fb711c9b.6dafd4f2.js",
          "hash": "ac7e5e7c5b416b74",
          "publicPath": "/assets/js/fb711c9b.6dafd4f2.js"
        }
      ]
    },
    "792": {
      "js": [
        {
          "file": "assets/js/main.0dba677c.js",
          "hash": "8cda17496787c7e9",
          "publicPath": "/assets/js/main.0dba677c.js"
        }
      ]
    },
    "849": {
      "js": [
        {
          "file": "assets/js/0058b4c6.c29f56bd.js",
          "hash": "ec22e789fedd21f3",
          "publicPath": "/assets/js/0058b4c6.c29f56bd.js"
        }
      ]
    },
    "869": {
      "css": [
        {
          "file": "assets/css/styles.e0330362.css",
          "hash": "87376e8b0ca2530a",
          "publicPath": "/assets/css/styles.e0330362.css"
        }
      ]
    },
    "897": {
      "js": [
        {
          "file": "assets/js/b30d0db9.fe558417.js",
          "hash": "6bb9c0fee129682c",
          "publicPath": "/assets/js/b30d0db9.fe558417.js"
        }
      ]
    },
    "955": {
      "js": [
        {
          "file": "assets/js/cd84c24b.df99d20d.js",
          "hash": "fc3a341a7cc507b3",
          "publicPath": "/assets/js/cd84c24b.df99d20d.js"
        }
      ]
    },
    "963": {
      "js": [
        {
          "file": "assets/js/95167d33.e16fd900.js",
          "hash": "ea638ebb45d39d19",
          "publicPath": "/assets/js/95167d33.e16fd900.js"
        }
      ]
    },
    "976": {
      "js": [
        {
          "file": "assets/js/0e384e19.dd4acc8c.js",
          "hash": "c111b5fe4b2c1dcb",
          "publicPath": "/assets/js/0e384e19.dd4acc8c.js"
        }
      ]
    }
  }
}